[
  {
    "function_name": "cognitive_model1",
    "metric_name": "BIC",
    "metric_value": 228.47686094059364,
    "param_names": [
      "lr",
      "softmax_beta",
      "gate_k",
      "gate_b",
      "wm_decay"
    ],
    "code_file": "/Users/milena.rmus/Desktop/gecco/results/rlwm_individual/models/iter4_run0_participant10.txt"
  },
  {
    "function_name": "cognitive_model2",
    "metric_name": "BIC",
    "metric_value": 233.4134588780431,
    "param_names": [
      "lr",
      "softmax_beta",
      "k_visit",
      "wm_refresh",
      "beta_mix"
    ],
    "code_file": "/Users/milena.rmus/Desktop/gecco/results/rlwm_individual/models/iter4_run0_participant10.txt"
  },
  {
    "function_name": "cognitive_model3",
    "metric_name": "BIC",
    "metric_value": 227.92552789124963,
    "param_names": [
      "lr",
      "softmax_beta",
      "arbit_temp",
      "wm_leak",
      "pe_sensitivity"
    ],
    "code_file": "/Users/milena.rmus/Desktop/gecco/results/rlwm_individual/models/iter4_run0_participant10.txt"
  }
]