[
  {
    "function_name": "cognitive_model1",
    "metric_name": "BIC",
    "metric_value": 516.6457473604935,
    "param_names": [
      "alpha",
      "beta1",
      "beta2",
      "w_mb_base",
      "lambda_base"
    ],
    "code_file": "/Users/milena.rmus/Desktop/gecco/results/two_step_task_individual/models/iter2_run0_participant16.txt"
  },
  {
    "function_name": "cognitive_model2",
    "metric_name": "BIC",
    "metric_value": 493.10054665914265,
    "param_names": [
      "alpha",
      "beta_base",
      "eta_base",
      "phi_base",
      "kappa"
    ],
    "code_file": "/Users/milena.rmus/Desktop/gecco/results/two_step_task_individual/models/iter2_run0_participant16.txt"
  },
  {
    "function_name": "cognitive_model3",
    "metric_name": "BIC",
    "metric_value": 507.8639801416241,
    "param_names": [
      "alpha",
      "beta1",
      "beta2_base",
      "psi_base",
      "omega"
    ],
    "code_file": "/Users/milena.rmus/Desktop/gecco/results/two_step_task_individual/models/iter2_run0_participant16.txt"
  }
]