[
  {
    "function_name": "cognitive_model1",
    "metric_name": "BIC",
    "metric_value": 395.78342521290506,
    "param_names": [
      "alpha",
      "beta",
      "interference_base",
      "load_interference_gain",
      "age_interference_gain"
    ],
    "code_file": "/Users/milena.rmus/Desktop/gecco/results/rlwm_individual/models/iter7_run0_participant9.txt"
  },
  {
    "function_name": "cognitive_model2",
    "metric_name": "BIC",
    "metric_value": 429.2649490625346,
    "param_names": [
      "alpha",
      "beta",
      "forget_base",
      "load_forget_gain",
      "age_temp_shift"
    ],
    "code_file": "/Users/milena.rmus/Desktop/gecco/results/rlwm_individual/models/iter7_run0_participant9.txt"
  },
  {
    "function_name": "cognitive_model3",
    "metric_name": "BIC",
    "metric_value": 393.9578030230983,
    "param_names": [
      "alpha",
      "beta",
      "rule_bias",
      "load_rule_gain",
      "age_rule_penalty"
    ],
    "code_file": "/Users/milena.rmus/Desktop/gecco/results/rlwm_individual/models/iter7_run0_participant9.txt"
  }
]