[
  {
    "function_name": "cognitive_model1",
    "metric_name": "BIC",
    "metric_value": 399.50727408472665,
    "param_names": [
      "lr",
      "beta_rl",
      "wm_base",
      "rl_unc_slope",
      "wm_unc_slope",
      "wm_decay"
    ],
    "code_file": "/Users/milena.rmus/Desktop/gecco/results/rlwm_individual/models/iter9_run0_participant44.txt"
  },
  {
    "function_name": "cognitive_model2",
    "metric_name": "BIC",
    "metric_value": 404.30294844716104,
    "param_names": [
      "lr",
      "beta_rl",
      "wm_weight0",
      "novelty_bonus",
      "wm_slots",
      "wm_decay"
    ],
    "code_file": "/Users/milena.rmus/Desktop/gecco/results/rlwm_individual/models/iter9_run0_participant44.txt"
  },
  {
    "function_name": "cognitive_model3",
    "metric_name": "BIC",
    "metric_value": 322.32237984618246,
    "param_names": [
      "lr_pos",
      "lr_neg",
      "beta_rl",
      "wm_weight0",
      "wsls_weight0",
      "wm_decay"
    ],
    "code_file": "/Users/milena.rmus/Desktop/gecco/results/rlwm_individual/models/iter9_run0_participant44.txt"
  }
]