[
  {
    "function_name": "cognitive_model1",
    "metric_name": "BIC",
    "metric_value": 533.8470612452965,
    "param_names": [
      "alpha",
      "beta",
      "w",
      "lambd",
      "kappa"
    ],
    "code_file": "/Users/milena.rmus/Desktop/gecco/results/two_step_task_individual/models/iter0_run0_participant43.txt"
  },
  {
    "function_name": "cognitive_model2",
    "metric_name": "BIC",
    "metric_value": 559.8010015171568,
    "param_names": [
      "alpha",
      "beta",
      "u_bonus",
      "eta"
    ],
    "code_file": "/Users/milena.rmus/Desktop/gecco/results/two_step_task_individual/models/iter0_run0_participant43.txt"
  },
  {
    "function_name": "cognitive_model3",
    "metric_name": "BIC",
    "metric_value": 552.1777679764614,
    "param_names": [
      "alpha_r",
      "alpha_t",
      "beta",
      "w",
      "rho"
    ],
    "code_file": "/Users/milena.rmus/Desktop/gecco/results/two_step_task_individual/models/iter0_run0_participant43.txt"
  }
]