[
  {
    "function_name": "cognitive_model1",
    "metric_name": "BIC",
    "metric_value": 377.4337489038111,
    "param_names": [
      "alpha",
      "beta",
      "omega0",
      "eta",
      "psi"
    ],
    "code_file": "/Users/milena.rmus/Desktop/gecco/results/two_step_task_individual/models/iter4_run0_participant34.txt"
  },
  {
    "function_name": "cognitive_model2",
    "metric_name": "BIC",
    "metric_value": 460.88151525595345,
    "param_names": [
      "alpha",
      "beta",
      "nu",
      "upsilon",
      "chi2"
    ],
    "code_file": "/Users/milena.rmus/Desktop/gecco/results/two_step_task_individual/models/iter4_run0_participant34.txt"
  },
  {
    "function_name": "cognitive_model3",
    "metric_name": "BIC",
    "metric_value": 349.6912267377247,
    "param_names": [
      "alpha",
      "beta",
      "lambda_u",
      "mu",
      "theta"
    ],
    "code_file": "/Users/milena.rmus/Desktop/gecco/results/two_step_task_individual/models/iter4_run0_participant34.txt"
  }
]