[
  {
    "function_name": "cognitive_model1",
    "metric_name": "BIC",
    "metric_value": 385.14859550017206,
    "param_names": [
      "alpha",
      "beta",
      "rho0",
      "age_slope",
      "load_slope"
    ],
    "code_file": "/Users/milena.rmus/Desktop/gecco/results/rlwm_individual/models/iter5_run0_participant4.txt"
  },
  {
    "function_name": "cognitive_model2",
    "metric_name": "BIC",
    "metric_value": 292.8429204344434,
    "param_names": [
      "alpha",
      "beta",
      "k_cap_base",
      "age_penalty",
      "epsilon"
    ],
    "code_file": "/Users/milena.rmus/Desktop/gecco/results/rlwm_individual/models/iter5_run0_participant4.txt"
  },
  {
    "function_name": "cognitive_model3",
    "metric_name": "BIC",
    "metric_value": 297.10404346431534,
    "param_names": [
      "alpha",
      "beta",
      "eta",
      "tau",
      "gain"
    ],
    "code_file": "/Users/milena.rmus/Desktop/gecco/results/rlwm_individual/models/iter5_run0_participant4.txt"
  }
]