[
  {
    "function_name": "cognitive_model1",
    "metric_name": "BIC",
    "metric_value": 383.4169150055608,
    "param_names": [
      "alpha_base",
      "beta_base",
      "kappa_age",
      "lambda_forget",
      "eps_base"
    ],
    "code_file": "/Users/milena.rmus/Desktop/gecco/results/rlwm_individual/models/iter3_run0_participant40.txt"
  },
  {
    "function_name": "cognitive_model2",
    "metric_name": "BIC",
    "metric_value": 354.9204450284842,
    "param_names": [
      "alpha",
      "beta",
      "valence_bias",
      "stick_age",
      "epsilon"
    ],
    "code_file": "/Users/milena.rmus/Desktop/gecco/results/rlwm_individual/models/iter3_run0_participant40.txt"
  },
  {
    "function_name": "cognitive_model3",
    "metric_name": "BIC",
    "metric_value": 381.25259153394705,
    "param_names": [
      "alpha",
      "beta",
      "K_base",
      "gate_temp",
      "epsilon"
    ],
    "code_file": "/Users/milena.rmus/Desktop/gecco/results/rlwm_individual/models/iter3_run0_participant40.txt"
  }
]