[
  {
    "function_name": "cognitive_model1",
    "metric_name": "BIC",
    "metric_value": 307.3875343229163,
    "param_names": [
      "lr",
      "softmax_beta",
      "wm_weight_base",
      "err_sensitivity",
      "age_err_delta",
      "size_err_delta"
    ],
    "code_file": "/Users/milena.rmus/Desktop/gecco/results/rlwm_individual/models/iter9_run0_participant22.txt"
  },
  {
    "function_name": "cognitive_model2",
    "metric_name": "BIC",
    "metric_value": 294.288195722499,
    "param_names": [
      "lr",
      "softmax_beta",
      "wm_weight_base",
      "interference_slope",
      "age_interf_delta",
      "wm_decay"
    ],
    "code_file": "/Users/milena.rmus/Desktop/gecco/results/rlwm_individual/models/iter9_run0_participant22.txt"
  },
  {
    "function_name": "cognitive_model3",
    "metric_name": "BIC",
    "metric_value": 296.4278410291961,
    "param_names": [
      "lr",
      "softmax_beta",
      "wm_beta_base",
      "wm_beta_age_penalty",
      "wm_beta_size_bonus",
      "wm_weight_base"
    ],
    "code_file": "/Users/milena.rmus/Desktop/gecco/results/rlwm_individual/models/iter9_run0_participant22.txt"
  }
]